schemafunc/__init__.py
schemafunc/exceptions.py
schemafunc/schemafunc.py
schemafunc/type_registry/__init__.py
schemafunc/type_registry/array.py
schemafunc/type_registry/basic_types.py
schemafunc/type_registry/literal.py
schemafunc/type_registry/mapping.py
schemafunc/type_registry/registry.py
schemafunc/type_registry/typed_dict.py
schemafunc/type_registry/union.py
schemafunc-0.3.19.dist-info/LICENSE
schemafunc-0.3.19.dist-info/METADATA
schemafunc-0.3.19.dist-info/WHEEL
schemafunc-0.3.19.dist-info/entry_points.txt
schemafunc-0.3.19.dist-info/RECORD
