Metadata-Version: 2.1
Name: schemafunc
Version: 0.3.19
Summary: Python function-to-LLM tool maker.
Home-page: https://github.com/dmwyatt/schemafunc
License: MIT
Keywords: python,openai,llm,language-model,schema,function,tool
Author: Dustin Wyatt
Author-email: dustin.wyatt@gmail.com
Requires-Python: >=3.10.11,<4.0.0
Classifier: Development Status :: 3 - Alpha
Classifier: Intended Audience :: Developers
Classifier: License :: OSI Approved :: MIT License
Classifier: Programming Language :: Python :: 3
Classifier: Programming Language :: Python :: 3.11
Classifier: Programming Language :: Python :: 3.12
Classifier: Programming Language :: Python :: 3.10
Classifier: Programming Language :: Python :: 3.8
Classifier: Programming Language :: Python :: 3.9
Classifier: Topic :: Software Development :: Libraries :: Python Modules
Classifier: Topic :: Utilities
Requires-Dist: docstring-parser (>=0.16,<0.17)
Project-URL: Repository, https://github.com/dmwyatt/schemafunc
